irontorch/__init__.py
irontorch/distributed/__init__.py
irontorch/distributed/comm.py
irontorch/distributed/config.py
irontorch/distributed/launch.py
irontorch/distributed/schema.py
irontorch/models/__init__.py
irontorch/models/ema.py
irontorch/recorder/__init__.py
irontorch/recorder/logging.py
irontorch/recorder/trackers.py
irontorch/utils/__init__.py
irontorch/utils/clip_grad.py
irontorch/utils/helper.py
irontorch/utils/scaler.py
irontorch-0.0.12.dist-info/licenses/LICENSE
irontorch-0.0.12.dist-info/METADATA
irontorch-0.0.12.dist-info/WHEEL
irontorch-0.0.12.dist-info/top_level.txt
irontorch-0.0.12.dist-info/RECORD
