Metadata-Version: 2.4
Name: irontorch
Version: 0.0.12
Summary: Developer-friendly Pytorch utility library
Home-page: https://github.com/thisisiron/irontorch
Author: Kim Eon
Author-email: kimiron518@gmail.com
License: MIT
License-File: LICENSE
Requires-Dist: torch>=1.1
Requires-Dist: pydantic>=1.8
Requires-Dist: omegaconf
Requires-Dist: rich
Requires-Dist: flake8
Requires-Dist: black
Dynamic: author
Dynamic: author-email
Dynamic: home-page
Dynamic: license
Dynamic: license-file
Dynamic: requires-dist
Dynamic: summary
